{"elapsed":"0.45","endpoint-url":"https://github.com/digital-land/ownership-status-collection/raw/main/data/ownership-status.csv","entry-date":"2022-03-03T00:19:58.156101","request-headers":{"Accept":"*/*","Accept-Encoding":"gzip, deflate","Connection":"keep-alive","User-Agent":"DLUHC Digital Land"},"resource":"20f351a015df7544a73c7ecfdf21dc575927b4812e54e85f98ae6aa5098d92ff","response-headers":{"Accept-Ranges":"bytes","Access-Control-Allow-Origin":"*","Cache-Control":"max-age=300","Connection":"keep-alive","Content-Encoding":"gzip","Content-Length":"153","Content-Security-Policy":"default-src 'none'; style-src 'unsafe-inline'; sandbox","Content-Type":"text/plain; charset=utf-8","Date":"Thu, 03 Mar 2022 00:19:58 GMT","ETag":"W/\"b78cfd81f30ba1066f14f7e7fd95eb7c1b950ae7420a2c11f4ce4d6f5156a753\"","Expires":"Thu, 03 Mar 2022 00:24:58 GMT","Source-Age":"0","Strict-Transport-Security":"max-age=31536000","Vary":"Authorization,Accept-Encoding,Origin","Via":"1.1 varnish","X-Cache":"MISS","X-Cache-Hits":"0","X-Content-Type-Options":"nosniff","X-Fastly-Request-ID":"de84ec67fa63d87df09ab07bd18ffcab2a86469c","X-Frame-Options":"deny","X-GitHub-Request-Id":"C148:84EF:1F8A51:284969:622009AE","X-Served-By":"cache-sjc10024-SJC","X-Timer":"S1646266799.634030,VS0,VE169","X-XSS-Protection":"1; mode=block"},"ssl-verify":true,"status":"200"}