{"elapsed":"0.256","endpoint-url":"https://github.com/digital-land/ownership-status-collection/raw/main/data/ownership-status.csv","entry-date":"2021-09-14T00:49:36.776061","request-headers":{"Accept":"*/*","Accept-Encoding":"gzip, deflate","Connection":"keep-alive","User-Agent":"Digital Land"},"resource":"20f351a015df7544a73c7ecfdf21dc575927b4812e54e85f98ae6aa5098d92ff","response-headers":{"Accept-Ranges":"bytes","Access-Control-Allow-Origin":"*","Cache-Control":"max-age=300","Connection":"keep-alive","Content-Encoding":"gzip","Content-Length":"153","Content-Security-Policy":"default-src 'none'; style-src 'unsafe-inline'; sandbox","Content-Type":"text/plain; charset=utf-8","Date":"Tue, 14 Sep 2021 00:49:37 GMT","ETag":"W/\"b78cfd81f30ba1066f14f7e7fd95eb7c1b950ae7420a2c11f4ce4d6f5156a753\"","Expires":"Tue, 14 Sep 2021 00:54:37 GMT","Source-Age":"0","Strict-Transport-Security":"max-age=31536000","Vary":"Authorization,Accept-Encoding,Origin","Via":"1.1 varnish","X-Cache":"MISS","X-Cache-Hits":"0","X-Content-Type-Options":"nosniff","X-Fastly-Request-ID":"d2d6f0839683f335a774cda67103b400021e7a11","X-Frame-Options":"deny","X-GitHub-Request-Id":"92F6:19E9:10E2AFD:1629D4B:613FF1A1","X-Served-By":"cache-bwi5049-BWI","X-Timer":"S1631580577.387932,VS0,VE96","X-XSS-Protection":"1; mode=block"},"ssl-verify":true,"status":"200"}